nr_common_metadata/__init__.py
nr_common_metadata/jsonschemas/__init__.py
nr_common_metadata/jsonschemas/nr_common_metadata/__init__.py
nr_common_metadata/jsonschemas/nr_common_metadata/nr-common-metadata-v1.0.0.json
nr_common_metadata/mapping_includes/__init__.py
nr_common_metadata/mapping_includes/v7/__init__.py
nr_common_metadata/mapping_includes/v7/nr-common-metadata-v1.0.0.json
nr_common_metadata/mapping_includes/v7/nr-taxonomies-accessRights-v1.0.0.json
nr_common_metadata/mapping_includes/v7/nr-taxonomies-contributor-v1.0.0.json
nr_common_metadata/mapping_includes/v7/nr-taxonomies-institution-v1.0.0.json
nr_common_metadata/mapping_includes/v7/nr-taxonomies-rights-v1.0.0.json
nr_common_metadata/mapping_includes/v7/nr-taxonomies-subject-v1.0.0.json
nr_common_metadata/mappings/__init__.py
nr_common_metadata/mappings/v7/__init__.py
nr_common_metadata/mappings/v7/nr_common_metadata/__init__.py
nr_common_metadata/marshmallow/__init__.py
nr_common_metadata/marshmallow/fields.py
nr_common_metadata/marshmallow/json.py
nr_common_metadata/marshmallow/subschemas.py
techlib_nr_common_metadata-3.0.0a49.dist-info/entry_points.txt
techlib_nr_common_metadata-3.0.0a49.dist-info/WHEEL
techlib_nr_common_metadata-3.0.0a49.dist-info/METADATA
techlib_nr_common_metadata-3.0.0a49.dist-info/RECORD
